LICENSE
README.md
setup.cfg
setup.py
docker_ascii_map/__init__.py
docker_ascii_map/argument_parser.py
docker_ascii_map/ascii_render.py
docker_ascii_map/debug.py
docker_ascii_map/docker-ascii-map
docker_ascii_map/docker_config.py
docker_ascii_map/raster.py
docker_ascii_map/widget.py
docker_ascii_map.egg-info/PKG-INFO
docker_ascii_map.egg-info/SOURCES.txt
docker_ascii_map.egg-info/dependency_links.txt
docker_ascii_map.egg-info/requires.txt
docker_ascii_map.egg-info/top_level.txt