Metadata-Version: 2.1
Name: docker-ascii-map
Version: 2.1.3
Summary: A set of python scripts displaying the local docker containers structure and status on an ascii map.
Home-page: https://gitlab.com/alcibiade/docker-ascii-map
Author: Yannick Kirschhoffer
Author-email: alcibiade@alcibiade.org
License: MIT
Platform: UNKNOWN
Classifier: Development Status :: 5 - Production/Stable
Classifier: Intended Audience :: Developers
Classifier: Intended Audience :: System Administrators
Classifier: Topic :: System :: Systems Administration
Classifier: License :: OSI Approved :: MIT License
Classifier: Programming Language :: Python :: 3
Classifier: Programming Language :: Python :: 3.5
License-File: LICENSE
